loadsure_data/__init__.py
loadsure_data/holistics_api.py
loadsure_data/sanctions_api.py
loadsure_data/sentry_api.py
loadsure_data-0.1.1.dist-info/LICENSE.txt
loadsure_data-0.1.1.dist-info/METADATA
loadsure_data-0.1.1.dist-info/WHEEL
loadsure_data-0.1.1.dist-info/top_level.txt
loadsure_data-0.1.1.dist-info/RECORD
